eyeglass/__init__.py
eyeglass/_version.py
eyeglass/plots.py
eyeglass-0.0.2.dist-info/LICENSE
eyeglass-0.0.2.dist-info/METADATA
eyeglass-0.0.2.dist-info/WHEEL
eyeglass-0.0.2.dist-info/top_level.txt
eyeglass-0.0.2.dist-info/RECORD
